pyalarmdotcomajax/__init__.py
pyalarmdotcomajax/__main__.py
pyalarmdotcomajax/cli.py
pyalarmdotcomajax/const.py
pyalarmdotcomajax/exceptions.py
pyalarmdotcomajax/extensions.py
pyalarmdotcomajax/helpers.py
pyalarmdotcomajax/devices/__init__.py
pyalarmdotcomajax/devices/camera.py
pyalarmdotcomajax/devices/garage_door.py
pyalarmdotcomajax/devices/gate.py
pyalarmdotcomajax/devices/image_sensor.py
pyalarmdotcomajax/devices/light.py
pyalarmdotcomajax/devices/lock.py
pyalarmdotcomajax/devices/partition.py
pyalarmdotcomajax/devices/registry.py
pyalarmdotcomajax/devices/sensor.py
pyalarmdotcomajax/devices/system.py
pyalarmdotcomajax/devices/thermostat.py
pyalarmdotcomajax/devices/water_sensor.py
pyalarmdotcomajax/websockets/__init__.py
pyalarmdotcomajax/websockets/client.py
pyalarmdotcomajax/websockets/const.py
pyalarmdotcomajax/websockets/messages.py
pyalarmdotcomajax/websockets/handler/__init__.py
pyalarmdotcomajax/websockets/handler/garage_door.py
pyalarmdotcomajax/websockets/handler/gate.py
pyalarmdotcomajax/websockets/handler/light.py
pyalarmdotcomajax/websockets/handler/lock.py
pyalarmdotcomajax/websockets/handler/partition.py
pyalarmdotcomajax/websockets/handler/sensor.py
pyalarmdotcomajax/websockets/handler/thermostat.py
pyalarmdotcomajax/websockets/handler/water_sensor.py
pyalarmdotcomajax-0.5.13.dist-info/licenses/LICENSE
tests/__init__.py
tests/conftest.py
tests/test_controller.py
tests/test_device_extensions.py
tests/test_partition.py
tests/test_sensors.py
tests/test_thermostat.py
tests/responses/__init__.py
pyalarmdotcomajax-0.5.13.dist-info/METADATA
pyalarmdotcomajax-0.5.13.dist-info/WHEEL
pyalarmdotcomajax-0.5.13.dist-info/entry_points.txt
pyalarmdotcomajax-0.5.13.dist-info/top_level.txt
pyalarmdotcomajax-0.5.13.dist-info/zip-safe
pyalarmdotcomajax-0.5.13.dist-info/RECORD
