Metadata-Version: 2.4
Name: pyalarmdotcomajax
Version: 0.5.13
Summary: Python Interface for Alarm.com
Home-page: https://github.com/pyalarmdotcom/pyalarmdotcomajax
Author: Justin Wong
Author-email: 46082645+uvjustin@users.noreply.github.com
Maintainer: Elahd Bar-Shai
Maintainer-email: 46082645+uvjustin@users.noreply.github.com, 466460+elahd@users.noreply.github.com
License: MIT
Keywords: Alarm.com,Security System,Home Assistant
Classifier: Development Status :: 5 - Production/Stable
Classifier: Natural Language :: English
Classifier: Environment :: Web Environment
Classifier: Intended Audience :: Developers
Classifier: Programming Language :: Python :: 3
Classifier: License :: OSI Approved :: MIT License
Classifier: Operating System :: OS Independent
Classifier: Topic :: Software Development :: Libraries :: Python Modules
Classifier: Topic :: Home Automation
Requires-Python: >=3.11
License-File: LICENSE
Requires-Dist: beautifulsoup4>=4.10.0
Requires-Dist: aiohttp>=3.8.1
Requires-Dist: python-dateutil>=2.8.2
Requires-Dist: termcolor>=2.1.1
Dynamic: license-file
